pyoccad/__init__.py
pyoccad/_version.py
pyoccad/typing.py
pyoccad/create/__init__.py
pyoccad/create/axis.py
pyoccad/create/axis_test.py
pyoccad/create/control_point.py
pyoccad/create/control_point_test.py
pyoccad/create/coord_system.py
pyoccad/create/coord_system_test.py
pyoccad/create/direction.py
pyoccad/create/direction_test.py
pyoccad/create/interpolation.py
pyoccad/create/interpolation_test.py
pyoccad/create/intersection.py
pyoccad/create/intersection_test.py
pyoccad/create/plane.py
pyoccad/create/plane_test.py
pyoccad/create/point.py
pyoccad/create/point_test.py
pyoccad/create/topology.py
pyoccad/create/topology_test.py
pyoccad/create/transformation.py
pyoccad/create/transformation_test.py
pyoccad/create/vector.py
pyoccad/create/vector_test.py
pyoccad/create/vertex.py
pyoccad/create/vertex_test.py
pyoccad/create/container/__init__.py
pyoccad/create/container/array.py
pyoccad/create/container/array_test.py
pyoccad/create/container/list.py
pyoccad/create/container/list_test.py
pyoccad/create/container/sequence.py
pyoccad/create/container/sequence_test.py
pyoccad/create/curve/__init__.py
pyoccad/create/curve/arc.py
pyoccad/create/curve/arc_test.py
pyoccad/create/curve/bezier.py
pyoccad/create/curve/bezier_test.py
pyoccad/create/curve/bspline.py
pyoccad/create/curve/bspline_builder_test.py
pyoccad/create/curve/bspline_test.py
pyoccad/create/curve/circle.py
pyoccad/create/curve/circle_test.py
pyoccad/create/curve/conic.py
pyoccad/create/curve/conic_test.py
pyoccad/create/curve/curve.py
pyoccad/create/curve/curve_test.py
pyoccad/create/curve/edge.py
pyoccad/create/curve/edge_test.py
pyoccad/create/curve/ellipse.py
pyoccad/create/curve/ellipse_test.py
pyoccad/create/curve/line.py
pyoccad/create/curve/line_test.py
pyoccad/create/curve/wire.py
pyoccad/create/curve/wire_test.py
pyoccad/create/primitive/__init__.py
pyoccad/create/primitive/extrusion.py
pyoccad/create/primitive/extrusion_test.py
pyoccad/create/primitive/offset.py
pyoccad/create/primitive/offset_test.py
pyoccad-0.6.0.dist-info/LICENSE
pyoccad-0.6.0.dist-info/METADATA
pyoccad-0.6.0.dist-info/WHEEL
pyoccad-0.6.0.dist-info/top_level.txt
pyoccad-0.6.0.dist-info/RECORD
