Metadata-Version: 2.1
Name: pyoccad
Version: 0.6.0
Summary: A geometrical modeler based on Open-Cascade
Home-page: https://pyoccad.readthedocs.io
Author: Adrien DELSALLE
License: Apache 2.0 License
Keywords: pyoccad,occt,opencascade
Classifier: Intended Audience :: End Users/Desktop
Classifier: Intended Audience :: Developers
Classifier: Intended Audience :: Science/Research
Classifier: License :: Other/Proprietary License
Classifier: Natural Language :: English
Classifier: Programming Language :: Python :: 3
Requires-Python: >=3.7
License-File: LICENSE
Requires-Dist: numpy >=1.14
Requires-Dist: scipy
Provides-Extra: extra
Requires-Dist: pythreejs ; extra == 'extra'
